transfusion_pytorch/__init__.py
transfusion_pytorch/transfusion.py
transfusion_pytorch-0.15.3.dist-info/METADATA
transfusion_pytorch-0.15.3.dist-info/WHEEL
transfusion_pytorch-0.15.3.dist-info/licenses/LICENSE
transfusion_pytorch-0.15.3.dist-info/RECORD
