Metadata-Version: 2.4
Name: transfusion-pytorch
Version: 0.15.3
Summary: Transfusion in Pytorch
Project-URL: Homepage, https://pypi.org/project/transfusion-pytorch/
Project-URL: Repository, https://github.com/lucidrains/transfusion-pytorch
Author-email: Phil Wang <lucidrains@gmail.com>
License: MIT License
License-File: LICENSE
Keywords: artificial intelligence,attention mechanism,deep learning,rectified flow,transformers
Classifier: Development Status :: 4 - Beta
Classifier: Intended Audience :: Developers
Classifier: License :: OSI Approved :: MIT License
Classifier: Programming Language :: Python :: 3.8
Classifier: Topic :: Scientific/Engineering :: Artificial Intelligence
Requires-Python: >=3.8
Requires-Dist: axial-positional-embedding>=0.3.5
Requires-Dist: beartype
Requires-Dist: einops>=0.8.0
Requires-Dist: einx>=0.3.0
Requires-Dist: ema-pytorch
Requires-Dist: hyper-connections>=0.3.12
Requires-Dist: jaxtyping
Requires-Dist: loguru
Requires-Dist: rotary-embedding-torch>=0.8.4
Requires-Dist: torch>=2.0
Requires-Dist: torchdiffeq
Requires-Dist: tqdm
Provides-Extra: examples
Requires-Dist: adam-atan2-pytorch>=0.2.2; extra == 'examples'
Requires-Dist: datasets; extra == 'examples'
Requires-Dist: diffusers; extra == 'examples'
Provides-Extra: test
Requires-Dist: pytest; extra == 'test'
